feml/__init__.py
feml/curvature.py
feml/measures.py
feml/metrics.py
feml/plotting.py
feml-0.0.1.dist-info/LICENSE
feml-0.0.1.dist-info/METADATA
feml-0.0.1.dist-info/WHEEL
feml-0.0.1.dist-info/top_level.txt
feml-0.0.1.dist-info/RECORD
