Metadata-Version: 2.1
Name: feml
Version: 0.0.1
Summary: Functionally-explained machine learning.
Author-email: Galen Seilis <galen.seilis@seilis.ca>
Project-URL: Homepage, https://github.com/galenseilis/feml
Project-URL: Bug Tracker, https://github.com/galenseilis/feml/issues
Classifier: Programming Language :: Python :: 3
Classifier: License :: OSI Approved :: MIT License
Classifier: Operating System :: OS Independent
Requires-Python: >=3.7
License-File: LICENSE
